_vaststream_pybind11.cpython-37m-x86_64-linux-gnu.so
libfn-log.so
libvace.so
libvacl.so
libvacm.so
libvame.so
libvaml.so
libvmpp-dec.so
libvmpp-enc.so
vaststream/VERSION
vaststream/__init__.py
vaststream/vace/__init__.py
vaststream/vace/common.py
vaststream/vace/op_attr_desc.py
vaststream/vace/op_base.py
vaststream/vace/op_custom.py
vaststream/vace/op_fusion.py
vaststream/vace/op_fusion_wrapper.py
vaststream/vace/op_single.py
vaststream/vace/temp.py
vaststream/vace/utils.py
vaststream/vace/vace_custom_op_example.py
vaststream/vacl/__init__.py
vaststream/vacl/common.py
vaststream/vacl/model.py
vaststream/vacl/stream.py
vaststream/vacl/streamOp.py
vaststream/vacl/temp.py
vaststream/vacl/utils.py
vaststream/vacm/__init__.py
vaststream/vacm/basic.py
vaststream/vacm/common.py
vaststream/vacm/context.py
vaststream/vacm/data.py
vaststream/vacm/databuffer.py
vaststream/vacm/dataset.py
vaststream/vacm/device.py
vaststream/vacm/env.py
vaststream/vacm/log.py
vaststream/vacm/memory.py
vaststream/vacm/os.py
vaststream/vacm/tensor.py
vaststream/vacm/utility.py
vaststream/vacm/utils.py
vaststream/vame/__init__.py
vaststream/vame/common.py
vaststream/vame/decoder.py
vaststream/vame/encoder.py
vaststream/vame/utils.py
vaststream/vame/videoCapture.py
vaststream/vaml/__init__.py
vaststream/vaml/callbackfunc.py
vaststream/vaml/card.py
vaststream/vaml/common.py
vaststream/vaml/device.py
vaststream/vaml/die.py
vaststream/vaml/profiler.py
vaststream/vaml/utils.py
vaststream-2.2.0.dist-info/METADATA
vaststream-2.2.0.dist-info/WHEEL
vaststream-2.2.0.dist-info/top_level.txt
vaststream-2.2.0.dist-info/RECORD
