Metadata-Version: 2.1
Name: vaststream
Version: 2.2.0
Summary: The SDK for vastai device.
Home-page: UNKNOWN
Author: Vastai Team
License: Apache-2.0 License
Platform: UNKNOWN
Classifier: License :: OSI Approved :: Apache Software License
Classifier: Operating System :: OS Independent
Classifier: Programming Language :: Python :: 3
Requires-Python: >=3
Requires-Dist: numpy
